cloudshell/__init__.py
cloudshell/shell/__init__.py
cloudshell/shell/standards/__init__.py
cloudshell/shell/standards/pdu/__init__.py
cloudshell/shell/standards/pdu/autoload_model.py
cloudshell/shell/standards/pdu/driver_interface.py
cloudshell/shell/standards/pdu/resource_config.py
tests/__init__.py
tests/conftest.py
tests/cloudshell/__init__.py
tests/cloudshell/shell_pdu_standards/__init__.py
tests/cloudshell/shell_pdu_standards/test_autoload_generic_models.py
tests/cloudshell/shell_pdu_standards/test_driver_interface.py
tests/cloudshell/shell_pdu_standards/test_resource_config.py
cloudshell_shell_pdu_standard-1.0.0.dist-info/LICENSE.htm
cloudshell_shell_pdu_standard-1.0.0.dist-info/METADATA
cloudshell_shell_pdu_standard-1.0.0.dist-info/WHEEL
cloudshell_shell_pdu_standard-1.0.0.dist-info/top_level.txt
cloudshell_shell_pdu_standard-1.0.0.dist-info/RECORD
